pyacadcom/__init__.py
pyacadcom/api.py
pyacadcom/datatype.py
pyacadcom/tool.py
pyacadcom/userinput.py
pyacadcom/utils.py
pyacadcom-0.0.10.dist-info/LICENSE.txt
pyacadcom-0.0.10.dist-info/METADATA
pyacadcom-0.0.10.dist-info/WHEEL
pyacadcom-0.0.10.dist-info/top_level.txt
pyacadcom-0.0.10.dist-info/RECORD
