Metadata-Version: 2.1
Name: pyacadcom
Version: 0.0.10
Summary: Python AutoCAD COM automation via pywin32
Home-page: http://github.com/lobyntsev-d/pyacadcom
Author: Dmitriy Lobyntsev
Author-email: dmitriy@lobyntsev.com
License: BSD License
Keywords: autocad,automation,activex,pywin32
Classifier: Programming Language :: Python
Classifier: License :: OSI Approved :: BSD License
Classifier: Development Status :: 4 - Beta
Classifier: Environment :: Win32 (MS Windows)
Classifier: Intended Audience :: Developers
Classifier: Operating System :: Microsoft :: Windows
Classifier: Topic :: Software Development :: Libraries :: Python Modules
Classifier: Topic :: Scientific/Engineering
License-File: LICENSE.txt
Requires-Dist: pywin32 (>=214)
